bitsandbytes/__init__.py
bitsandbytes/__main__.py
bitsandbytes/cextension.py
bitsandbytes/functional.py
bitsandbytes/utils.py
bitsandbytes/autograd/__init__.py
bitsandbytes/autograd/_functions.py
bitsandbytes/cuda_setup/__init__.py
bitsandbytes/cuda_setup/env_vars.py
bitsandbytes/cuda_setup/libbitsandbytes_cuda116.dll
bitsandbytes/cuda_setup/main.py
bitsandbytes/nn/__init__.py
bitsandbytes/nn/modules.py
bitsandbytes/optim/__init__.py
bitsandbytes/optim/adagrad.py
bitsandbytes/optim/adam.py
bitsandbytes/optim/adamw.py
bitsandbytes/optim/lamb.py
bitsandbytes/optim/lars.py
bitsandbytes/optim/optimizer.py
bitsandbytes/optim/rmsprop.py
bitsandbytes/optim/sgd.py
bitsandbytes_windows-0.37.5.dist-info/LICENSE
bitsandbytes_windows-0.37.5.dist-info/METADATA
bitsandbytes_windows-0.37.5.dist-info/NOTICE.md
bitsandbytes_windows-0.37.5.dist-info/WHEEL
bitsandbytes_windows-0.37.5.dist-info/top_level.txt
bitsandbytes_windows-0.37.5.dist-info/RECORD
