Metadata-Version: 2.1
Name: bitsandbytes-windows
Version: 0.37.5
Summary: 8-bit optimizers and matrix multiplication routines.
Home-page: https://github.com/Keith-Hon/bitsandbytes-windows
Author: Tim Dettmers
Author-email: dettmers@cs.washington.edu
License: MIT
Keywords: gpu optimizers optimization 8-bit quantization compression
Platform: UNKNOWN
Classifier: Development Status :: 4 - Beta
Classifier: Topic :: Scientific/Engineering :: Artificial Intelligence
License-File: LICENSE
License-File: NOTICE.md
